adi_doctools/__init__.py
adi_doctools/lut.py
adi_doctools/.ruff_cache/.gitignore
adi_doctools/.ruff_cache/CACHEDIR.TAG
adi_doctools/.ruff_cache/0.14.2/11026909506114179896
adi_doctools/.ruff_cache/0.14.2/8180311997241503430
adi_doctools/cli/__init__.py
adi_doctools/cli/aggregate.py
adi_doctools/cli/aux_cover.py
adi_doctools/cli/aux_git.py
adi_doctools/cli/aux_html2md.py
adi_doctools/cli/aux_os.py
adi_doctools/cli/aux_print.py
adi_doctools/cli/custom_doc.py
adi_doctools/cli/hdl_gen.py
adi_doctools/cli/hdl_render.py
adi_doctools/cli/search.py
adi_doctools/cli/serve.py
adi_doctools/cli/.ruff_cache/.gitignore
adi_doctools/cli/.ruff_cache/CACHEDIR.TAG
adi_doctools/cli/.ruff_cache/0.14.2/5482709810473481639
adi_doctools/directive/__init__.py
adi_doctools/directive/common.py
adi_doctools/directive/hdl.py
adi_doctools/directive/node.py
adi_doctools/directive/string.py
adi_doctools/directive/system_top.py
adi_doctools/miscellaneous/dev-pool.js
adi_doctools/miscellaneous/esd-warning.svg
adi_doctools/miscellaneous/third-party.css
adi_doctools/monkeypatch/__init__.py
adi_doctools/parser/__init__.py
adi_doctools/parser/hdl.py
adi_doctools/parser/tcl.py
adi_doctools/role/__init__.py
adi_doctools/role/common.py
adi_doctools/role/interref.py
adi_doctools/theme/__init__.py
adi_doctools/theme/harmonic.py
adi_doctools/theme/cosmic/static/app.umd.js
adi_doctools/theme/cosmic/static/app.umd.js.map
adi_doctools/theme/cosmic/static/doxygen.umd.js
adi_doctools/theme/cosmic/static/doxygen.umd.js.map
adi_doctools/theme/cosmic/static/extra.umd.js
adi_doctools/theme/cosmic/static/extra.umd.js.map
adi_doctools/theme/harmonic/layout.html
adi_doctools/theme/harmonic/search.html
adi_doctools/theme/harmonic/theme.conf
adi_doctools/theme/harmonic/scripts/app.js
adi_doctools/theme/harmonic/scripts/content_actions.js
adi_doctools/theme/harmonic/scripts/dom.js
adi_doctools/theme/harmonic/scripts/doxygen.js
adi_doctools/theme/harmonic/scripts/event.js
adi_doctools/theme/harmonic/scripts/extra.js
adi_doctools-0.4.32.dist-info/entry_points.txt
adi_doctools-0.4.32.dist-info/licenses/LICENSE
adi_doctools-0.4.32.dist-info/WHEEL
adi_doctools-0.4.32.dist-info/METADATA
adi_doctools-0.4.32.dist-info/RECORD
