Metadata-Version: 2.4
Name: adi-doctools
Version: 0.4.32
Summary: ADI's sphinx extensions and theme
Author-email: Jorge Marques <jorge.marques@analog.com>
Requires-Python: >=3.8
Classifier: Development Status :: 1 - Planning
Classifier: Framework :: Sphinx
Classifier: Framework :: Sphinx :: Theme
Classifier: Framework :: Sphinx :: Extension
Classifier: Intended Audience :: Developers
Classifier: License :: OSI Approved :: BSD License
Classifier: Operating System :: OS Independent
Classifier: Programming Language :: Python :: 3
Classifier: Programming Language :: Python :: Implementation :: CPython
Classifier: Topic :: Software Development :: Documentation
Classifier: Topic :: Text Processing :: Markup
Classifier: Topic :: Text Processing :: Markup :: reStructuredText
License-File: LICENSE
Requires-Dist: docutils
Requires-Dist: sphinx
Requires-Dist: lxml
Requires-Dist: click
Requires-Dist: pygments >= 2.7
Requires-Dist: PyYAML
Requires-Dist: selenium ; extra == "cli"
Requires-Dist: weasyprint ; extra == "cli"
Requires-Dist: pytest ; extra == "test"
Requires-Dist: ruff ; extra == "test"
Provides-Extra: cli
Provides-Extra: test
